xnattagger/__init__.py
xnattagger/__version__.py
xnattagger/config/__init__.py
xnattagger/config/tagger.yaml
xnattagger-0.8.0.data/scripts/xnat_tagger.py
xnattagger-0.8.0.dist-info/licenses/LICENSE
xnattagger-0.8.0.dist-info/METADATA
xnattagger-0.8.0.dist-info/WHEEL
xnattagger-0.8.0.dist-info/top_level.txt
xnattagger-0.8.0.dist-info/RECORD
