Metadata-Version: 2.4
Name: xnattagger
Version: 0.8.0
Summary: XNAT Tagger
Home-page: https://github.com/harvard-nrg/xnattagger
Author: Neuroinformatics Research Group
Author-email: info@neuroinfo.org
License-File: LICENSE
Requires-Dist: yaxil
Requires-Dist: pyaml
Dynamic: author
Dynamic: author-email
Dynamic: home-page
Dynamic: license-file
Dynamic: requires-dist
Dynamic: summary
